CONTRIBUTING.rst
HISTORY.rst
LICENSE
MANIFEST.in
README.rst
setup.cfg
setup.py
fastGRAHSP/GALAGN128.json
fastGRAHSP/GALAGN128.onnx
fastGRAHSP/GALAGN256.json
fastGRAHSP/GALAGN256.onnx
fastGRAHSP/__init__.py
fastGRAHSP.egg-info/PKG-INFO
fastGRAHSP.egg-info/SOURCES.txt
fastGRAHSP.egg-info/dependency_links.txt
fastGRAHSP.egg-info/requires.txt
fastGRAHSP.egg-info/top_level.txt
fastGRAHSP/xray/__init__.py
fastGRAHSP/xray/toruscruxux-28-0.1-avg-400-0.01.txt.gz
fastGRAHSP/xray/toruscruxux-28-0.1-avg-400-0.1.txt.gz
fastGRAHSP/xray/toruscruxux-28-0.1-avg-400-0.txt.gz
fastGRAHSP/xray/toruscruxux-28-0.2-avg-400-0.01.txt.gz
fastGRAHSP/xray/toruscruxux-28-0.2-avg-400-0.1.txt.gz
fastGRAHSP/xray/toruscruxux-28-0.2-avg-400-0.txt.gz
fastGRAHSP/xray/toruscruxux-28-0.4-avg-400-0.01.txt.gz
fastGRAHSP/xray/toruscruxux-28-0.4-avg-400-0.1.txt.gz
fastGRAHSP/xray/toruscruxux-28-0.4-avg-400-0.txt.gz
fastGRAHSP/xray/toruscruxux-60-0-avg-400-0.01.txt.gz
fastGRAHSP/xray/toruscruxux-60-0-avg-400-0.1.txt.gz
fastGRAHSP/xray/toruscruxux-60-0-avg-400-0.txt.gz
fastGRAHSP/xray/toruscruxux-60-0.1-avg-400-0.01.txt.gz
fastGRAHSP/xray/toruscruxux-60-0.1-avg-400-0.1.txt.gz
fastGRAHSP/xray/toruscruxux-60-0.1-avg-400-0.txt.gz
fastGRAHSP/xray/toruscruxux-8-0.1-avg-300-0.txt.gz
fastGRAHSP/xray/toruscruxux-8-0.1-avg-400-0.01.txt.gz
fastGRAHSP/xray/toruscruxux-8-0.1-avg-400-0.1.txt.gz
fastGRAHSP/xray/toruscruxux-8-0.1-avg-400-0.txt.gz
fastGRAHSP/xray/toruscruxux-8-0.4-avg-400-0.01.txt.gz
fastGRAHSP/xray/toruscruxux-8-0.4-avg-400-0.1.txt.gz
fastGRAHSP/xray/toruscruxux-8-0.4-avg-400-0.txt.gz
tests/test_fastgrahsp.py
tests/test_xray.py