Metadata-Version: 2.2
Name: fastGRAHSP
Version: 1.0.3
Summary: Fast neural network simulator for fluxes of galaxies and quasars.
Home-page: https://github.com/JohannesBuchner/fastGRAHSP
Author: Johannes Buchner
Author-email: johannes.buchner.acad@gmx.com
License: GNU General Public License v3
Keywords: neural network emulator,astronomy,galaxies,quasars
Classifier: Development Status :: 2 - Pre-Alpha
Classifier: Intended Audience :: Developers
Classifier: License :: OSI Approved :: GNU General Public License v3 (GPLv3)
Classifier: Natural Language :: English
Classifier: Programming Language :: Python :: 3
Classifier: Programming Language :: Python :: 3.5
Classifier: Programming Language :: Python :: 3.6
Classifier: Programming Language :: Python :: 3.7
Classifier: Programming Language :: Python :: 3.8
Classifier: Programming Language :: Python :: 3.9
Classifier: Programming Language :: Python :: 3.10
Classifier: Programming Language :: Python :: 3.11
Classifier: Programming Language :: Python :: 3.12
Requires-Python: >=3.7
License-File: LICENSE
Requires-Dist: numpy
Requires-Dist: scipy
Requires-Dist: onnxruntime
Provides-Extra: plot
Requires-Dist: matplotlib; extra == "plot"
Requires-Dist: scipy; extra == "plot"
Dynamic: author
Dynamic: author-email
Dynamic: classifier
Dynamic: description
Dynamic: description-content-type
Dynamic: home-page
Dynamic: keywords
Dynamic: license
Dynamic: provides-extra
Dynamic: requires-dist
Dynamic: requires-python
Dynamic: summary
